smappdragon/__init__.py
smappdragon/collection/__init__.py
smappdragon/collection/base_collection.py
smappdragon/collection/mongo_collection.py
smappdragon/tools/__init__.py
smappdragon/tools/tweet_parser.py
smappdragon-0.0.4.dist-info/DESCRIPTION.rst
smappdragon-0.0.4.dist-info/METADATA
smappdragon-0.0.4.dist-info/metadata.json
smappdragon-0.0.4.dist-info/RECORD
smappdragon-0.0.4.dist-info/top_level.txt
smappdragon-0.0.4.dist-info/WHEEL
