Metadata-Version: 2.0
Name: smappdragon
Version: 0.0.4
Summary: smappdragon is a set of tools for working with twitter data
Home-page: https://github.com/SMAPPNYU/smappdragon
Author: yvan
Author-email: yns207@nyu.edu
License: MIT
Keywords: twitter parse smappdragon
Platform: UNKNOWN
Requires-Dist: pymongo (>=3.2.1)
